core_apis/__init__.py
core_apis/py.typed
core_apis/api/__init__.py
core_apis/api/server.py
core_apis/api/routers/__init__.py
core_apis/api/routers/health.py
core_apis/decorators/__init__.py
core_apis/decorators/response_wrapper.py
core_apis/tests/__init__.py
core_apis/tests/base.py
core_apis/tests/runner.py
core_apis-1.0.0.dist-info/licenses/LICENSE
core_apis-1.0.0.dist-info/METADATA
core_apis-1.0.0.dist-info/WHEEL
core_apis-1.0.0.dist-info/top_level.txt
core_apis-1.0.0.dist-info/RECORD
