Metadata-Version: 2.4
Name: core-apis
Version: 1.0.0
Summary: This project/library contains useful elements related to APIs...
Author-email: Alejandro Cora González <alek.cora.glez@gmail.com>
Maintainer: Alejandro Cora González
License: MIT
Project-URL: Homepage, https://gitlab.com/bytecode-solutions/core/core-apis
Project-URL: Repository, https://gitlab.com/bytecode-solutions/core/core-apis
Project-URL: Documentation, https://core-apis.readthedocs.io/en/latest/
Project-URL: Issues, https://gitlab.com/bytecode-solutions/core/core-apis/-/issues
Project-URL: Changelog, https://gitlab.com/bytecode-solutions/core/core-apis/-/blob/master/CHANGELOG.md
Classifier: License :: OSI Approved :: MIT License
Classifier: Intended Audience :: Developers
Classifier: Development Status :: 5 - Production/Stable
Classifier: Topic :: Software Development :: Libraries :: Python Modules
Classifier: Topic :: Utilities
Classifier: Programming Language :: Python
Classifier: Programming Language :: Python :: 3
Classifier: Programming Language :: Python :: 3 :: Only
Classifier: Programming Language :: Python :: 3.9
Classifier: Programming Language :: Python :: 3.10
Classifier: Programming Language :: Python :: 3.11
Classifier: Programming Language :: Python :: 3.12
Classifier: Programming Language :: Python :: 3.13
Requires-Python: >=3.9
License-File: LICENSE
Requires-Dist: core-https>=2.0.1
Requires-Dist: core-tests>=2.0.2
Requires-Dist: fastapi>=0.115.6; python_version >= "3.8"
Requires-Dist: uvicorn>=0.34.0; python_version >= "3.9"
Provides-Extra: dev
Requires-Dist: core-dev-tools>=1.0.1; extra == "dev"
Requires-Dist: httpx>=0.28.1; python_version >= "3.9" and extra == "dev"
Dynamic: license-file
